correlationMatrix/__init__.py
correlationMatrix/model.py
correlationMatrix/settings.py
correlationMatrix/utils/__init__.py
correlationMatrix/utils/converters.py
correlationMatrix/utils/dataset_generators.py
correlationMatrix/utils/fetch_equity_data.py
correlationMatrix/utils/preprocessing.py
datasets/SectorsNCompanies.py
datasets/SingleFactor.json
datasets/__init__.py
datasets/json_example.csv
datasets/json_example.json
datasets/json_example_log_returns.csv
datasets/json_example_scaled_returns.csv
datasets/yahoo_log_returns.csv
datasets/yahoo_merged_data.csv
datasets/yahoo_scaled_returns.csv
datasets/__pycache__/SectorsNCompanies.cpython-35.pyc
datasets/__pycache__/SectorsNCompanies.cpython-38.pyc
datasets/__pycache__/__init__.cpython-34.pyc
datasets/__pycache__/__init__.cpython-35.pyc
datasets/__pycache__/__init__.cpython-38.pyc
datasets/yahoo_equity_data/AAPL.csv
datasets/yahoo_equity_data/ADM.csv
datasets/yahoo_equity_data/AIG.csv
datasets/yahoo_equity_data/ALL.csv
datasets/yahoo_equity_data/AMZN.csv
datasets/yahoo_equity_data/APC.csv
datasets/yahoo_equity_data/AXP.csv
datasets/yahoo_equity_data/BAC.csv
datasets/yahoo_equity_data/C.csv
datasets/yahoo_equity_data/CAH.csv
datasets/yahoo_equity_data/CI.csv
datasets/yahoo_equity_data/CL.csv
datasets/yahoo_equity_data/COP.csv
datasets/yahoo_equity_data/CSCO.csv
datasets/yahoo_equity_data/CVS.csv
datasets/yahoo_equity_data/CVX.csv
datasets/yahoo_equity_data/DGX.csv
datasets/yahoo_equity_data/EOG.csv
datasets/yahoo_equity_data/F.csv
datasets/yahoo_equity_data/GIS.csv
datasets/yahoo_equity_data/GOOGL.csv
datasets/yahoo_equity_data/GS.csv
datasets/yahoo_equity_data/HAL.csv
datasets/yahoo_equity_data/HPQ.csv
datasets/yahoo_equity_data/HUM.csv
datasets/yahoo_equity_data/IBM.csv
datasets/yahoo_equity_data/INTC.csv
datasets/yahoo_equity_data/JPM.csv
datasets/yahoo_equity_data/KO.csv
datasets/yahoo_equity_data/LH.csv
datasets/yahoo_equity_data/MDLZ.csv
datasets/yahoo_equity_data/MO.csv
datasets/yahoo_equity_data/MS.csv
correlationMatrix-0.2.0.dist-info/LICENSE.txt
correlationMatrix-0.2.0.dist-info/METADATA
correlationMatrix-0.2.0.dist-info/WHEEL
correlationMatrix-0.2.0.dist-info/top_level.txt
correlationMatrix-0.2.0.dist-info/RECORD
